mail_pigeon/__init__.py
mail_pigeon/async_client.py
mail_pigeon/exceptions.py
mail_pigeon/mail_client.py
mail_pigeon/translate.py
mail_pigeon/utils.py
mail_pigeon/async_server/__init__.py
mail_pigeon/async_server/commands.py
mail_pigeon/async_server/mail_server.py
mail_pigeon/locale/en/LC_MESSAGES/mail_pigeon.mo
mail_pigeon/locale/en/LC_MESSAGES/mail_pigeon.po
mail_pigeon/mail_server/__init__.py
mail_pigeon/mail_server/commands.py
mail_pigeon/mail_server/mail_server.py
mail_pigeon/queue/__init__.py
mail_pigeon/queue/base_async_queue.py
mail_pigeon/queue/base_queue.py
mail_pigeon/queue/files_box.py
mail_pigeon/queue/simple_box.py
mail_pigeon/security/__init__.py
mail_pigeon/security/base.py
mail_pigeon/security/hmac.py
mail_pigeon-1.6.15.dist-info/licenses/LICENSE
mail_pigeon-1.6.15.dist-info/METADATA
mail_pigeon-1.6.15.dist-info/WHEEL
mail_pigeon-1.6.15.dist-info/top_level.txt
mail_pigeon-1.6.15.dist-info/RECORD
