Metadata-Version: 2.4
Name: mail_pigeon
Version: 1.6.15
Summary: Асинхронная клиент-серверная библиотека с файловой очередью на стороне клиента.
Author: Антон Глызин
Author-email: tosha.glyzin@mail.ru
License: MIT
Project-URL: Releases, https://github.com/AntonGlyzin/mail_pigeon/releases
Project-URL: Github, https://github.com/AntonGlyzin/mail_pigeon
Project-URL: Read the docs, https://mail-pigeon.readthedocs.io/ru/stable
Keywords: zmq files queue client server python
Classifier: Intended Audience :: Developers
Classifier: Programming Language :: Python :: 3.9
Classifier: Programming Language :: Python :: 3.10
Classifier: Programming Language :: Python :: 3.11
Classifier: Programming Language :: Python :: 3.12
Classifier: Programming Language :: Python :: 3.13
Classifier: Topic :: Software Development :: Libraries
Requires-Python: >=3.9
License-File: LICENSE
Requires-Dist: pyzmq<=27.0.2
Requires-Dist: psutil<=7.0.0
Requires-Dist: cryptography<=46.0.1
Requires-Dist: anyio<=4.12.0
Requires-Dist: tornado>=6.1
Dynamic: author
Dynamic: author-email
Dynamic: classifier
Dynamic: description
Dynamic: description-content-type
Dynamic: keywords
Dynamic: license
Dynamic: license-file
Dynamic: project-url
Dynamic: requires-dist
Dynamic: requires-python
Dynamic: summary
